{"Nodes":[],"ExecutionTime":"2024-01-05T09:54:36.9448471Z","GenerationTime":"0001-01-01T00:00:00","PluginUserSpecFlowId":"2bdbfe12-d06c-4c1f-919d-f5caa7310fcd","CLIUserSpecFlowId":null,"ExecutionResults":[{"ContextType":"Scenario","FeatureFolderPath":"Features","FeatureTitle":"Calculator","ScenarioTitle":"Multiplication","ScenarioArguments":[],"Status":"OK","StepResults":[{"Duration":"00:00:00.0009093","Status":"OK","Error":null,"Outputs":null},{"Duration":"00:00:00.0001286","Status":"OK","Error":null,"Outputs":null},{"Duration":"00:00:00.0002249","Status":"OK","Error":null,"Outputs":null},{"Duration":"00:00:00.0057767","Status":"OK","Error":null,"Outputs":null}],"Outputs":null},{"ContextType":"Scenario","FeatureFolderPath":"Features","FeatureTitle":"Calculator","ScenarioTitle":"Division","ScenarioArguments":[],"Status":"OK","StepResults":[{"Duration":"00:00:00.0000316","Status":"OK","Error":null,"Outputs":null},{"Duration":"00:00:00.0000131","Status":"OK","Error":null,"Outputs":null},{"Duration":"00:00:00.0002482","Status":"OK","Error":null,"Outputs":null},{"Duration":"00:00:00.0000203","Status":"OK","Error":null,"Outputs":null}],"Outputs":null},{"ContextType":"Scenario","FeatureFolderPath":"Features","FeatureTitle":"Calculator","ScenarioTitle":"Subtraction","ScenarioArguments":[],"Status":"OK","StepResults":[{"Duration":"00:00:00.0000191","Status":"OK","Error":null,"Outputs":null},{"Duration":"00:00:00.0000098","Status":"OK","Error":null,"Outputs":null},{"Duration":"00:00:00.0001794","Status":"OK","Error":null,"Outputs":null},{"Duration":"00:00:00.0000111","Status":"OK","Error":null,"Outputs":null}],"Outputs":null}],"StepReports":null}